appeal/__init__.py
appeal/argument_grouping.py
appeal/cpp.py
appeal/text.py
appeal/want_prints.py
appeal-0.6.3.dist-info/LICENSE
appeal-0.6.3.dist-info/WHEEL
appeal-0.6.3.dist-info/METADATA
appeal-0.6.3.dist-info/RECORD
