Metadata-Version: 2.1
Name: appeal
Version: 0.6.3
Summary: A powerful & Pythonic command-line parsing library.  Give your program Appeal!
Author-email: Larry Hastings <larry@hastings.org>
Requires-Python: >=3.6
Classifier: Intended Audience :: Developers
Classifier: License :: OSI Approved :: MIT License
Classifier: Programming Language :: Python :: 3
Classifier: Programming Language :: Python :: 3.6
Classifier: Programming Language :: Python :: 3.7
Classifier: Programming Language :: Python :: 3.8
Classifier: Programming Language :: Python :: 3.9
Classifier: Programming Language :: Python :: 3.10
Classifier: Programming Language :: Python :: 3.11
Classifier: Programming Language :: Python :: 3.12
Requires-Dist: big >= 0.12
Requires-Dist: perky ; extra == "dev"
Requires-Dist: tomli ; extra == "dev"
Project-URL: Source, https://github.com/larryhastings/appeal/
Provides-Extra: dev
